nomad_parser_plugins_workflow-1.1.10.dist-info/licenses/LICENSE
workflowparsers/__init__.py
workflowparsers/aflow/README.md
workflowparsers/aflow/__init__.py
workflowparsers/aflow/__main__.py
workflowparsers/aflow/nomad_plugin.yaml
workflowparsers/aflow/parser.py
workflowparsers/aflow/metainfo/__init__.py
workflowparsers/aflow/metainfo/aflow.py
workflowparsers/asr/README.md
workflowparsers/asr/__init__.py
workflowparsers/asr/__main__.py
workflowparsers/asr/nomad_plugin.yaml
workflowparsers/asr/parser.py
workflowparsers/asr/metainfo/__init__.py
workflowparsers/asr/metainfo/asr.py
workflowparsers/atomate/README.md
workflowparsers/atomate/__init__.py
workflowparsers/atomate/__main__.py
workflowparsers/atomate/nomad_plugin.yaml
workflowparsers/atomate/parser.py
workflowparsers/atomate/metainfo/__init__.py
workflowparsers/atomate/metainfo/atomate.py
workflowparsers/elastic/README.md
workflowparsers/elastic/__init__.py
workflowparsers/elastic/__main__.py
workflowparsers/elastic/nomad_plugin.yaml
workflowparsers/elastic/parser.py
workflowparsers/elastic/metainfo/__init__.py
workflowparsers/elastic/metainfo/elastic.py
workflowparsers/fhivibes/README.md
workflowparsers/fhivibes/__init__.py
workflowparsers/fhivibes/__main__.py
workflowparsers/fhivibes/nomad_plugin.yaml
workflowparsers/fhivibes/parser.py
workflowparsers/fhivibes/metainfo/__init__.py
workflowparsers/fhivibes/metainfo/fhi_vibes.py
workflowparsers/lobster/README.md
workflowparsers/lobster/__init__.py
workflowparsers/lobster/__main__.py
workflowparsers/lobster/nomad_plugin.yaml
workflowparsers/lobster/parser.py
workflowparsers/lobster/metainfo/__init__.py
workflowparsers/lobster/metainfo/lobster.py
workflowparsers/phonopy/README.md
workflowparsers/phonopy/__init__.py
workflowparsers/phonopy/__main__.py
workflowparsers/phonopy/calculator.py
workflowparsers/phonopy/nomad_plugin.yaml
workflowparsers/phonopy/parser.py
workflowparsers/phonopy/metainfo/__init__.py
workflowparsers/phonopy/metainfo/phonopy.py
workflowparsers/quantum_espresso_epw/README.md
nomad_parser_plugins_workflow-1.1.10.dist-info/METADATA
nomad_parser_plugins_workflow-1.1.10.dist-info/WHEEL
nomad_parser_plugins_workflow-1.1.10.dist-info/entry_points.txt
nomad_parser_plugins_workflow-1.1.10.dist-info/top_level.txt
nomad_parser_plugins_workflow-1.1.10.dist-info/RECORD
