Metadata-Version: 2.4
Name: nomad-parser-plugins-workflow
Version: 1.1.10
Summary: Collection of NOMAD parsers for workflow engines.
Author: The NOMAD Authors
License: 
Project-URL: homepage, https://github.com/nomad-coe/workflow-parsers
License-File: LICENSE
Requires-Dist: nomad-lab[infrastructure]>=1.3.13
Requires-Dist: nomad-schema-plugin-simulation-workflow>=1.0.1
Requires-Dist: nomad-schema-plugin-run>=1.0.1
Requires-Dist: lxml>=5.2
Requires-Dist: asr==0.4.1
Requires-Dist: xarray>=0.20.1
Requires-Dist: phonopy<=2.38,>=2.35
Requires-Dist: h5py>=3.11.0
Requires-Dist: pydantic>=1.10.8
Requires-Dist: netcdf4
Requires-Dist: h5netcdf
Provides-Extra: tests
Requires-Dist: astroid==2.11.7; extra == "tests"
Requires-Dist: mypy>=1.15; extra == "tests"
Requires-Dist: pytest<8,>=5.3.0; extra == "tests"
Requires-Dist: pytest-timeout>=1.4.2; extra == "tests"
Requires-Dist: pytest-cov>=2.7.1; extra == "tests"
Requires-Dist: ruff>=0.6; extra == "tests"
Requires-Dist: typing-extensions>=4.12; extra == "tests"
Requires-Dist: coverage; extra == "tests"
Requires-Dist: coveralls; extra == "tests"
Requires-Dist: types-PyYAML; extra == "tests"
Dynamic: license-file
